twitter_api/__init__.py
twitter_api/x_posting_api.py
x_posting_api/__init__.py
x_posting_api/x_posting_api.py
x_posting_api-0.4.dist-info/LICENCE
x_posting_api-0.4.dist-info/METADATA
x_posting_api-0.4.dist-info/WHEEL
x_posting_api-0.4.dist-info/top_level.txt
x_posting_api-0.4.dist-info/RECORD
