Metadata-Version: 2.1
Name: x_posting_api
Version: 0.4
Summary: A simple Python library for posting tweets using new X API v2.
Home-page: https://github.com/redianmarku/x-posting-api
Author: Redian Marku
Author-email: redian@topnotch-programmer.com
Classifier: Programming Language :: Python :: 3
Classifier: License :: OSI Approved :: MIT License
Classifier: Operating System :: OS Independent
License-File: LICENCE
Requires-Dist: requests-oauthlib
